LICENSE
MANIFEST.in
README.md
VERSION
setup.py
kondo/__init__.py
kondo/experiment.py
kondo/hparams.py
kondo/param_types.py
kondo/utils.py
kondo.egg-info/PKG-INFO
kondo.egg-info/SOURCES.txt
kondo.egg-info/dependency_links.txt
kondo.egg-info/requires.txt
kondo.egg-info/top_level.txt