Metadata-Version: 2.1
Name: kondo
Version: 0.7.0
Summary: Does your experiment spark joy?
Home-page: https://github.com/activatedgeek/kondo
Author: Sanyam Kapoor
License: Apache License 2.0
Platform: UNKNOWN
Classifier: Development Status :: 4 - Beta
Classifier: Intended Audience :: Developers
Classifier: Intended Audience :: Science/Research
Classifier: License :: OSI Approved :: Apache Software License
Classifier: Programming Language :: Python :: 3.6
Classifier: Programming Language :: Python :: 3.7
Classifier: Topic :: Scientific/Engineering :: Artificial Intelligence
Requires-Python: >=3.6, <4
Provides-Extra: all
